ctf_builder/__init__.py
ctf_builder/cli.py
ctf_builder/config.py
ctf_builder/docker.py
ctf_builder/error.py
ctf_builder/cmd/__init__.py
ctf_builder/cmd/build.py
ctf_builder/cmd/cli.py
ctf_builder/cmd/common.py
ctf_builder/cmd/documentation.py
ctf_builder/cmd/schema.py
ctf_builder/cmd/test.py
ctf_builder/cmd/ctfd/__init__.py
ctf_builder/cmd/ctfd/challenges.py
ctf_builder/cmd/ctfd/dev.py
ctf_builder/cmd/ctfd/setup.py
ctf_builder/cmd/ctfd/teams.py
ctf_builder/cmd/docker/__init__.py
ctf_builder/cmd/docker/deploy.py
ctf_builder/cmd/docker/list.py
ctf_builder/cmd/docker/start.py
ctf_builder/cmd/docker/stop.py
ctf_builder/cmd/k8s/__init__.py
ctf_builder/cmd/k8s/build.py
ctf_builder/ctfd/__init__.py
ctf_builder/ctfd/api.py
ctf_builder/ctfd/docker.py
ctf_builder/ctfd/models.py
ctf_builder/ctfd/session.py
ctf_builder/k8s/__init__.py
ctf_builder/k8s/models.py
ctf_builder/models/__init__.py
ctf_builder/models/arguments.py
ctf_builder/models/attachment.py
ctf_builder/models/challenge.py
ctf_builder/models/file.py
ctf_builder/models/flag.py
ctf_builder/models/healthcheck.py
ctf_builder/models/hint.py
ctf_builder/models/path.py
ctf_builder/models/port.py
ctf_builder/models/team.py
ctf_builder/models/text.py
ctf_builder/models/user.py
ctf_builder/models/build/__init__.py
ctf_builder/models/build/base.py
ctf_builder/models/build/docker.py
ctf_builder/models/deploy/__init__.py
ctf_builder/models/deploy/base.py
ctf_builder/models/deploy/cpu.py
ctf_builder/models/deploy/docker.py
ctf_builder/models/deploy/memory.py
ctf_builder/models/test/__init__.py
ctf_builder/models/test/base.py
ctf_builder/models/test/docker.py
tests/__init__.py
tests/integration/__init__.py
tests/integration/test_build.py
tests/integration/test_cli.py
tests/integration/test_ctfd.py
tests/integration/test_deploy.py
tests/integration/test_documentation.py
tests/integration/test_k8s.py
tests/integration/test_list.py
tests/integration/test_schema.py
tests/integration/test_test.py
ctf_builder-0.0.23.dist-info/LICENSE.txt
ctf_builder-0.0.23.dist-info/METADATA
ctf_builder-0.0.23.dist-info/WHEEL
ctf_builder-0.0.23.dist-info/entry_points.txt
ctf_builder-0.0.23.dist-info/top_level.txt
ctf_builder-0.0.23.dist-info/RECORD
