Metadata-Version: 2.1
Name: ctf-builder
Version: 0.0.23
Summary: Tool for building CTFs
Home-page: https://github.com/alexandre-lavoie/ctf-builder
Author: Alexandre Lavoie
Author-email: alexandre.lavoie00@gmail.com
License: MIT
Platform: UNKNOWN
Classifier: Programming Language :: Python :: 3
Classifier: License :: OSI Approved :: MIT License
Classifier: Operating System :: OS Independent
Requires-Python: >=3.8
Requires-Dist: requests==2.32.3
Requires-Dist: docker==7.1.0
Requires-Dist: rich==13.7.1
Requires-Dist: pydantic==2.8.2
